s3pyo
