Metadata-Version: 1.1
Name: s3pyo
Version: 0.0.3
Summary: A polite interface for sending python objects to and from Amazon S3.
Home-page: https://github.com/enigma-io/s3pyo
Author: Brian Abelson
Author-email: brian@enigma.io
License: MIT
Keywords: s3,aws
Platform: UNKNOWN
Classifier: Development Status :: 3 - Alpha
Classifier: Topic :: Communications :: Email
Classifier: License :: OSI Approved :: MIT License
